{"res": 0, "data": {"id": "29728", "category": "0", "display_category": 6, "item_id": "4960", "title": "摄影", "forward": "这实际上不是我自己决定的。是命运强加给我的。同我的工作一样，同我身上发生的一切事一样。说来不是我做事，而是事做我。", "img_url": "http://image.wufazhuce.com/FhkzXB5sOqasZMkcIBjVubz8hss8", "pic_ipX": "http://image.wufazhuce.com/FhkzXB5sOqasZMkcIBjVubz8hss8", "like_count": 5213, "post_date": "2025-12-10 06:00:00", "last_update_date": "2025-10-21 12:10:19", "author": {}, "video_url": "", "audio_url": "", "audio_platform": 2, "start_video": "", "has_reading": 0, "volume": "VOL.4813", "pic_info": "Fern M Lomibao", "words_info": "马里奥·巴尔加斯·略萨", "text_author_info": {"text_author_name": "马里奥·巴尔加斯·略萨", "text_author_work": "from 《酒吧长谈》", "text_author_desc": "著名作家，世界小说大师，被誉为“结构现实主义大师”，囊获全球重要文学大奖，包括诺贝尔文学奖：1985年获海明威文学奖，1986年获西班牙阿里图里亚斯王子文学奖，1988年获美洲金质奖章，1994年获西班牙文学的最高荣誉——塞万提斯文学奖，1999年获以色列耶路撒冷文学奖，2000年获梅嫩德斯·佩拉约国际奖，1976年被推选为国际笔会主席，2010年获诺贝尔文学奖。"}, "subtitle": "", "number": 0, "serial_id": 0, "serial_list": [], "movie_story_id": 0, "ad_id": 0, "ad_type": 0, "ad_pvurl": "", "ad_linkurl": "", "ad_makettime": "", "ad_closetime": "", "ad_share_cnt": "", "ad_pvurl_vendor": "", "content_id": "4960", "content_type": "0", "content_bgcolor": "", "share_url": "http://m.wufazhuce.com/one/4960", "share_info": {"url": "http://m.wufazhuce.com/one/4960", "image": "http://image.wufazhuce.com/FhkzXB5sOqasZMkcIBjVubz8hss8", "title": "VOL.4813", "content": "这实际上不是我自己决定的。是命运强加给我的。同我的工作一样，同我身上发生的一切事一样。说来不是我做事，而是事做我。 by 马里奥·巴尔加斯·略萨"}, "share_list": {"wx": {"title": "", "desc": "", "link": "http://m.wufazhuce.com/one/4960?channel=singlemessage", "imgUrl": "", "audio": ""}, "wx_timeline": {"title": "", "desc": "", "link": "http://m.wufazhuce.com/one/4960?channel=timeline", "imgUrl": "", "audio": ""}, "weibo": {"title": "ONE一个 这实际上不是我自己决定的。是命运强加给我的。同我的工作一样，同我身上发生的一切事一样。说来不是我做事，而是事做我。 by 马里奥·巴尔加斯·略萨——马里奥·巴尔加斯·略萨 下载ONE一个APP:http://weibo.com/p/100404157874", "desc": "", "link": "http://m.wufazhuce.com/one/4960?channel=weibo", "imgUrl": "", "audio": ""}, "qq": {"title": "", "desc": "", "link": "http://m.wufazhuce.com/one/4960?channel=qq", "imgUrl": "", "audio": ""}}, "tag_list": [], "orientation": "0", "weather": {"city_name": "地球", "date": "2025-12-11", "temperature": "-273.15", "humidity": "120", "climate": "对流层", "wind_direction": "一阵妖风", "hurricane": "36级", "icons": {"day": "weather_icon_unknown", "night": "weather_icon_unknown_night"}}}}