{"res": 0, "data": {"id": "29101", "category": "0", "display_category": 6, "item_id": "4783", "title": "摄影", "forward": "我惶惑一时，怕自己存在得毫无来由，如同一根悬空而生的蘑菇。", "img_url": "http://image.wufazhuce.com/FkdNP5ucI8MDh8lBHqANUV3LzZ7S", "pic_ipX": "http://image.wufazhuce.com/FkdNP5ucI8MDh8lBHqANUV3LzZ7S", "like_count": 4872, "post_date": "2025-06-25 06:05:00", "last_update_date": "2025-05-27 17:11:14", "author": {}, "video_url": "", "audio_url": "", "audio_platform": 2, "start_video": "", "has_reading": 0, "volume": "VOL.4645", "pic_info": "Chris Weiher", "words_info": "《造物须臾》", "text_author_info": {"text_author_name": "《造物须臾》", "text_author_work": "by 牛健哲", "text_author_desc": "《造物须臾》获第八届郁达夫小说奖。在本书中，作者牛健哲大胆想象：有没有一种可能？世界不止发端一两次，只要找到一个开关，它就能无限次重启。在每一个维度，我可能是一根悬空而生的蘑菇，也可能会忽然出现在生命垂暮的陌生人床上，或者还能变成一头非洲雄狮……何为万物？是先我存在微小如我无从把握的瀑流，还是因我而变却始终将我封闭其中的牢笼？"}, "subtitle": "", "number": 0, "serial_id": 0, "serial_list": [], "movie_story_id": 0, "ad_id": 0, "ad_type": 0, "ad_pvurl": "", "ad_linkurl": "", "ad_makettime": "", "ad_closetime": "", "ad_share_cnt": "", "ad_pvurl_vendor": "", "content_id": "4783", "content_type": "0", "content_bgcolor": "", "share_url": "http://m.wufazhuce.com/one/4783", "share_info": {"url": "http://m.wufazhuce.com/one/4783", "image": "http://image.wufazhuce.com/FkdNP5ucI8MDh8lBHqANUV3LzZ7S", "title": "VOL.4645", "content": "我惶惑一时，怕自己存在得毫无来由，如同一根悬空而生的蘑菇。 from 《造物须臾》"}, "share_list": {"wx": {"title": "", "desc": "", "link": "http://m.wufazhuce.com/one/4783?channel=singlemessage", "imgUrl": "", "audio": ""}, "wx_timeline": {"title": "", "desc": "", "link": "http://m.wufazhuce.com/one/4783?channel=timeline", "imgUrl": "", "audio": ""}, "weibo": {"title": "ONE一个 我惶惑一时，怕自己存在得毫无来由，如同一根悬空而生的蘑菇。 from 《造物须臾》——《造物须臾》 下载ONE一个APP:http://weibo.com/p/100404157874", "desc": "", "link": "http://m.wufazhuce.com/one/4783?channel=weibo", "imgUrl": "", "audio": ""}, "qq": {"title": "", "desc": "", "link": "http://m.wufazhuce.com/one/4783?channel=qq", "imgUrl": "", "audio": ""}}, "tag_list": [], "orientation": "0", "weather": {"city_name": "地球", "date": "2025-06-25", "temperature": "-273.15", "humidity": "120", "climate": "对流层", "wind_direction": "一阵妖风", "hurricane": "36级", "icons": {"day": "weather_icon_unknown", "night": "weather_icon_unknown_night"}}}}